rootdump/__init__.py
rootdump/core.py
rootdump/__pycache__/__init__.cpython-312.pyc
rootdump/__pycache__/core.cpython-312.pyc
rootdump-1.0.0.dist-info/LICENSE
rootdump-1.0.0.dist-info/METADATA
rootdump-1.0.0.dist-info/WHEEL
rootdump-1.0.0.dist-info/entry_points.txt
rootdump-1.0.0.dist-info/top_level.txt
rootdump-1.0.0.dist-info/RECORD
