Metadata-Version: 2.2
Name: rootdump
Version: 1.0.0
Summary: Directory content dumping utility
Author-email: Hirotaka Hiraki <hirotakahiraki@gmail.com>
License: MIT License
Project-URL: Homepage, https://github.com/hirotakahiraki/rootdump
Project-URL: Repository, https://github.com/hirotakahiraki/rootdump
Classifier: Development Status :: 3 - Alpha
Classifier: Intended Audience :: Developers
Classifier: License :: OSI Approved :: MIT License
Classifier: Programming Language :: Python :: 3
Classifier: Programming Language :: Python :: 3.6
Classifier: Programming Language :: Python :: 3.7
Classifier: Programming Language :: Python :: 3.8
Classifier: Programming Language :: Python :: 3.9
Classifier: Programming Language :: Python :: 3.10
Classifier: Programming Language :: Python :: 3.11
Classifier: Programming Language :: Python :: 3.12
Requires-Python: >=3.6
License-File: LICENSE
Requires-Dist: pathspec>=0.10.0
